wfdemo/__init__.py
wfdemo/api/__init__.py
wfdemo/api/image.py
wfdemo/core/ImageType.py
wfdemo/core/__init__.py
wfdemo/lib/__init__.py
wfdemo/lib/image/__init__.py
wfdemo/lib/image/add_watermark_service.py
wfdemo/lib/image/eliminate_background.py
wfdemo-0.0.2.dist-info/LICENSE
wfdemo-0.0.2.dist-info/METADATA
wfdemo-0.0.2.dist-info/WHEEL
wfdemo-0.0.2.dist-info/top_level.txt
wfdemo-0.0.2.dist-info/RECORD
